LOLLOL/Vir.py
LOLLOL/__init__.py
LOLLOL-0.1.1.dist-info/LICENSE
LOLLOL-0.1.1.dist-info/METADATA
LOLLOL-0.1.1.dist-info/WHEEL
LOLLOL-0.1.1.dist-info/top_level.txt
LOLLOL-0.1.1.dist-info/RECORD
