Metadata-Version: 2.1
Name: LOLLOL
Version: 0.1.1
Summary: Retrieve local, global, external ipaddress.
Home-page: https://github.com/ABIRHOSSAIN10
Author: ABIR HOSSAIN
Author-email: abirhossain200019@gmail.com
License: MIT
Keywords: python
Platform: UNKNOWN
Classifier: License :: OSI Approved :: MIT License
Classifier: Programming Language :: Python :: 3.6
Classifier: Programming Language :: Python :: 3.7
Classifier: Programming Language :: Python :: 3.8
Classifier: Programming Language :: Python :: 3.9
Classifier: Operating System :: Unix
Classifier: Operating System :: Microsoft :: Windows
License-File: LICENSE
Requires-Dist: mechanize
Requires-Dist: requests
